aplib.py
aplib-0.6.dist-info/LICENSE
aplib-0.6.dist-info/METADATA
aplib-0.6.dist-info/WHEEL
aplib-0.6.dist-info/top_level.txt
aplib-0.6.dist-info/RECORD
