Metadata-Version: 2.1
Name: aplib
Version: 0.6
Summary: Module for decompressing aPLib compressed data
Author: Sandor Nemes
License:                     GNU GENERAL PUBLIC LICENSE
Project-URL: Homepage, https://github.com/snemes/aplib
Classifier: Programming Language :: Python :: 2
Classifier: Programming Language :: Python :: 3
Classifier: License :: OSI Approved :: GNU General Public License v3 (GPLv3)
Classifier: Operating System :: OS Independent
Requires-Python: >=2.7
License-File: LICENSE
